setup.py
trtpy/__addition__.py
trtpy/__init__.py
trtpy/__main__.py
trtpy/downloader.py
trtpy/environment-template.sh
trtpy/init_default.py
trtpy/onnxtool.py
trtpy/process_code_template.py
trtpy.egg-info/PKG-INFO
trtpy.egg-info/SOURCES.txt
trtpy.egg-info/dependency_links.txt
trtpy.egg-info/not-zip-safe
trtpy.egg-info/requires.txt
trtpy.egg-info/top_level.txt
trtpy/include/app/yolo.hpp
trtpy/include/builder/trt_builder.hpp
trtpy/include/common/cuda_tools.hpp
trtpy/include/common/face_detector.hpp
trtpy/include/common/ilogger.hpp
trtpy/include/common/infer_controller.hpp
trtpy/include/common/json.hpp
trtpy/include/common/monopoly_allocator.hpp
trtpy/include/common/object_detector.hpp
trtpy/include/common/preprocess_kernel.cuh
trtpy/include/common/pybind11.hpp
trtpy/include/common/trt_image.hpp
trtpy/include/common/trt_tensor.hpp
trtpy/include/infer/trt_infer.hpp
trtpy/include/onnx/onnx-ml.pb.h
trtpy/include/onnx/onnx-operators-ml.pb.h
trtpy/include/onnx_parser/NvOnnxParser.h
trtpy/include/onnxplugin/onnxplugin.hpp
trtpy/include/onnxplugin/plugin_binary_io.hpp
trtpy/tensorrt/__init__.py