Metadata-Version: 2.1
Name: trtpy
Version: 1.2
Summary: TensorRTPro python interface
Home-page: https://github.com/shouxieai/tensorRT_cpp
Author: djw.hope
Author-email: 512690069@qq.com
License: UNKNOWN
Platform: linux
Requires-Python: >=3.6
